{
    "ar_SA": {
        "reviewed_percentage": "0%", 
        "completed": "7%", 
        "untranslated_words": 510, 
        "last_commiter": "", 
        "reviewed": 0, 
        "translated_entities": 10, 
        "translated_words": 17, 
        "last_update": "2016-03-06 20:52:39", 
        "untranslated_entities": 120
    }, 
    "eo": {
        "reviewed_percentage": "0%", 
        "completed": "0%", 
        "untranslated_words": 525, 
        "last_commiter": "", 
        "reviewed": 0, 
        "translated_entities": 1, 
        "translated_words": 2, 
        "last_update": "2016-03-06 20:52:39", 
        "untranslated_entities": 129
    }, 
    "sk_SK": {
        "reviewed_percentage": "0%", 
        "completed": "17%", 
        "untranslated_words": 476, 
        "last_commiter": "", 
        "reviewed": 0, 
        "translated_entities": 23, 
        "translated_words": 51, 
        "last_update": "2016-03-06 20:52:39", 
        "untranslated_entities": 107
    }, 
    "szl": {
        "reviewed_percentage": "0%", 
        "completed": "15%", 
        "untranslated_words": 482, 
        "last_commiter": "", 
        "reviewed": 0, 
        "translated_entities": 20, 
        "translated_words": 45, 
        "last_update": "2016-03-06 20:52:39", 
        "untranslated_entities": 110
    }, 
    "fi_FI": {
        "reviewed_percentage": "0%", 
        "completed": "17%", 
        "untranslated_words": 476, 
        "last_commiter": "", 
        "reviewed": 0, 
        "translated_entities": 23, 
        "translated_words": 51, 
        "last_update": "2016-03-06 20:52:39", 
        "untranslated_entities": 107
    }, 
    "hi_IN": {
        "reviewed_percentage": "0%", 
        "completed": "0%", 
        "untranslated_words": 525, 
        "last_commiter": "", 
        "reviewed": 0, 
        "translated_entities": 1, 
        "translated_words": 2, 
        "last_update": "2016-03-06 20:52:39", 
        "untranslated_entities": 129
    }, 
    "pt_PT": {
        "reviewed_percentage": "0%", 
        "completed": "17%", 
        "untranslated_words": 476, 
        "last_commiter": "", 
        "reviewed": 0, 
        "translated_entities": 23, 
        "translated_words": 51, 
        "last_update": "2016-03-06 20:52:39", 
        "untranslated_entities": 107
    }, 
    "it_IT": {
        "reviewed_percentage": "0%", 
        "completed": "17%", 
        "untranslated_words": 476, 
        "last_commiter": "", 
        "reviewed": 0, 
        "translated_entities": 23, 
        "translated_words": 51, 
        "last_update": "2016-03-06 20:52:39", 
        "untranslated_entities": 107
    }, 
    "et_EE": {
        "reviewed_percentage": "0%", 
        "completed": "7%", 
        "untranslated_words": 510, 
        "last_commiter": "", 
        "reviewed": 0, 
        "translated_entities": 10, 
        "translated_words": 17, 
        "last_update": "2016-03-06 20:52:39", 
        "untranslated_entities": 120
    }, 
    "sr_RS": {
        "reviewed_percentage": "0%", 
        "completed": "17%", 
        "untranslated_words": 476, 
        "last_commiter": "", 
        "reviewed": 0, 
        "translated_entities": 23, 
        "translated_words": 51, 
        "last_update": "2016-03-06 20:52:39", 
        "untranslated_entities": 107
    }, 
    "vi_VN": {
        "reviewed_percentage": "0%", 
        "completed": "6%", 
        "untranslated_words": 511, 
        "last_commiter": "", 
        "reviewed": 0, 
        "translated_entities": 9, 
        "translated_words": 16, 
        "last_update": "2016-03-06 20:52:39", 
        "untranslated_entities": 121
    }, 
    "uk_UA": {
        "reviewed_percentage": "0%", 
        "completed": "17%", 
        "untranslated_words": 476, 
        "last_commiter": "", 
        "reviewed": 0, 
        "translated_entities": 23, 
        "translated_words": 51, 
        "last_update": "2016-03-06 20:52:39", 
        "untranslated_entities": 107
    }, 
    "el_GR": {
        "reviewed_percentage": "0%", 
        "completed": "23%", 
        "untranslated_words": 458, 
        "last_commiter": "giokarinos", 
        "reviewed": 0, 
        "translated_entities": 31, 
        "translated_words": 69, 
        "last_update": "2016-03-06 21:06:10", 
        "untranslated_entities": 99
    }, 
    "nl_NL": {
        "reviewed_percentage": "0%", 
        "completed": "17%", 
        "untranslated_words": 476, 
        "last_commiter": "", 
        "reviewed": 0, 
        "translated_entities": 23, 
        "translated_words": 51, 
        "last_update": "2016-03-06 20:52:39", 
        "untranslated_entities": 107
    }, 
    "en_US": {
        "reviewed_percentage": "0%", 
        "completed": "17%", 
        "untranslated_words": 476, 
        "last_commiter": "", 
        "reviewed": 0, 
        "translated_entities": 23, 
        "translated_words": 51, 
        "last_update": "2016-03-06 20:52:39", 
        "untranslated_entities": 107
    }, 
    "lv_LV": {
        "reviewed_percentage": "0%", 
        "completed": "7%", 
        "untranslated_words": 510, 
        "last_commiter": "", 
        "reviewed": 0, 
        "translated_entities": 10, 
        "translated_words": 17, 
        "last_update": "2016-03-06 20:52:39", 
        "untranslated_entities": 120
    }, 
    "ta_IN": {
        "reviewed_percentage": "0%", 
        "completed": "5%", 
        "untranslated_words": 514, 
        "last_commiter": "", 
        "reviewed": 0, 
        "translated_entities": 7, 
        "translated_words": 13, 
        "last_update": "2016-03-06 20:52:39", 
        "untranslated_entities": 123
    }, 
    "cy_GB": {
        "reviewed_percentage": "0%", 
        "completed": "7%", 
        "untranslated_words": 510, 
        "last_commiter": "", 
        "reviewed": 0, 
        "translated_entities": 10, 
        "translated_words": 17, 
        "last_update": "2016-03-06 20:52:39", 
        "untranslated_entities": 120
    }, 
    "th_TH": {
        "reviewed_percentage": "0%", 
        "completed": "17%", 
        "untranslated_words": 476, 
        "last_commiter": "", 
        "reviewed": 0, 
        "translated_entities": 23, 
        "translated_words": 51, 
        "last_update": "2016-03-06 20:52:39", 
        "untranslated_entities": 107
    }, 
    "be_BY": {
        "reviewed_percentage": "0%", 
        "completed": "6%", 
        "untranslated_words": 511, 
        "last_commiter": "", 
        "reviewed": 0, 
        "translated_entities": 9, 
        "translated_words": 16, 
        "last_update": "2016-03-06 20:52:39", 
        "untranslated_entities": 121
    }, 
    "mk_MK": {
        "reviewed_percentage": "0%", 
        "completed": "7%", 
        "untranslated_words": 510, 
        "last_commiter": "", 
        "reviewed": 0, 
        "translated_entities": 10, 
        "translated_words": 17, 
        "last_update": "2016-03-06 20:52:39", 
        "untranslated_entities": 120
    }, 
    "pl_PL": {
        "reviewed_percentage": "0%", 
        "completed": "17%", 
        "untranslated_words": 476, 
        "last_commiter": "", 
        "reviewed": 0, 
        "translated_entities": 23, 
        "translated_words": 51, 
        "last_update": "2016-03-06 20:52:39", 
        "untranslated_entities": 107
    }, 
    "ro_RO": {
        "reviewed_percentage": "0%", 
        "completed": "17%", 
        "untranslated_words": 476, 
        "last_commiter": "", 
        "reviewed": 0, 
        "translated_entities": 23, 
        "translated_words": 51, 
        "last_update": "2016-03-06 20:52:39", 
        "untranslated_entities": 107
    }, 
    "fr_FR": {
        "reviewed_percentage": "0%", 
        "completed": "17%", 
        "untranslated_words": 476, 
        "last_commiter": "", 
        "reviewed": 0, 
        "translated_entities": 23, 
        "translated_words": 51, 
        "last_update": "2016-03-06 20:52:39", 
        "untranslated_entities": 107
    }, 
    "ca_ES": {
        "reviewed_percentage": "0%", 
        "completed": "17%", 
        "untranslated_words": 476, 
        "last_commiter": "", 
        "reviewed": 0, 
        "translated_entities": 23, 
        "translated_words": 51, 
        "last_update": "2016-03-06 20:52:39", 
        "untranslated_entities": 107
    }, 
    "az_AZ": {
        "reviewed_percentage": "0%", 
        "completed": "0%", 
        "untranslated_words": 527, 
        "last_commiter": "", 
        "reviewed": 0, 
        "translated_entities": 0, 
        "translated_words": 0, 
        "last_update": "2016-03-06 20:51:08", 
        "untranslated_entities": 130
    }, 
    "id_ID": {
        "reviewed_percentage": "0%", 
        "completed": "17%", 
        "untranslated_words": 476, 
        "last_commiter": "", 
        "reviewed": 0, 
        "translated_entities": 23, 
        "translated_words": 51, 
        "last_update": "2016-03-06 20:52:39", 
        "untranslated_entities": 107
    }, 
    "sr_RS@latin": {
        "reviewed_percentage": "0%", 
        "completed": "17%", 
        "untranslated_words": 476, 
        "last_commiter": "", 
        "reviewed": 0, 
        "translated_entities": 23, 
        "translated_words": 51, 
        "last_update": "2016-03-06 20:52:39", 
        "untranslated_entities": 107
    }, 
    "en_AU": {
        "reviewed_percentage": "0%", 
        "completed": "7%", 
        "untranslated_words": 510, 
        "last_commiter": "", 
        "reviewed": 0, 
        "translated_entities": 10, 
        "translated_words": 17, 
        "last_update": "2016-03-06 20:52:39", 
        "untranslated_entities": 120
    }, 
    "hu_HU": {
        "reviewed_percentage": "0%", 
        "completed": "17%", 
        "untranslated_words": 476, 
        "last_commiter": "", 
        "reviewed": 0, 
        "translated_entities": 23, 
        "translated_words": 51, 
        "last_update": "2016-03-06 20:52:39", 
        "untranslated_entities": 107
    }, 
    "ja_JP": {
        "reviewed_percentage": "0%", 
        "completed": "7%", 
        "untranslated_words": 510, 
        "last_commiter": "", 
        "reviewed": 0, 
        "translated_entities": 10, 
        "translated_words": 17, 
        "last_update": "2016-03-06 20:52:39", 
        "untranslated_entities": 120
    }, 
    "lt_LT": {
        "reviewed_percentage": "0%", 
        "completed": "30%", 
        "untranslated_words": 402, 
        "last_commiter": "Zapata11", 
        "reviewed": 0, 
        "translated_entities": 39, 
        "translated_words": 125, 
        "last_update": "2016-03-07 07:23:07", 
        "untranslated_entities": 91
    }, 
    "sl_SI": {
        "reviewed_percentage": "0%", 
        "completed": "17%", 
        "untranslated_words": 476, 
        "last_commiter": "", 
        "reviewed": 0, 
        "translated_entities": 23, 
        "translated_words": 51, 
        "last_update": "2016-03-06 20:52:39", 
        "untranslated_entities": 107
    }, 
    "hr_HR": {
        "reviewed_percentage": "0%", 
        "completed": "17%", 
        "untranslated_words": 476, 
        "last_commiter": "", 
        "reviewed": 0, 
        "translated_entities": 23, 
        "translated_words": 51, 
        "last_update": "2016-03-06 20:52:39", 
        "untranslated_entities": 107
    }, 
    "es_AR": {
        "reviewed_percentage": "0%", 
        "completed": "17%", 
        "untranslated_words": 476, 
        "last_commiter": "", 
        "reviewed": 0, 
        "translated_entities": 23, 
        "translated_words": 51, 
        "last_update": "2016-03-06 20:52:39", 
        "untranslated_entities": 107
    }, 
    "eu_ES": {
        "reviewed_percentage": "0%", 
        "completed": "7%", 
        "untranslated_words": 510, 
        "last_commiter": "", 
        "reviewed": 0, 
        "translated_entities": 10, 
        "translated_words": 17, 
        "last_update": "2016-03-06 20:52:39", 
        "untranslated_entities": 120
    }, 
    "es_ES": {
        "reviewed_percentage": "0%", 
        "completed": "17%", 
        "untranslated_words": 476, 
        "last_commiter": "", 
        "reviewed": 0, 
        "translated_entities": 23, 
        "translated_words": 51, 
        "last_update": "2016-03-06 20:52:39", 
        "untranslated_entities": 107
    }, 
    "gl_ES": {
        "reviewed_percentage": "0%", 
        "completed": "17%", 
        "untranslated_words": 476, 
        "last_commiter": "", 
        "reviewed": 0, 
        "translated_entities": 23, 
        "translated_words": 51, 
        "last_update": "2016-03-06 20:52:39", 
        "untranslated_entities": 107
    }, 
    "en_GB": {
        "reviewed_percentage": "0%", 
        "completed": "100%", 
        "untranslated_words": 0, 
        "last_commiter": "TeamKODI", 
        "reviewed": 0, 
        "translated_entities": 130, 
        "translated_words": 527, 
        "last_update": "2016-03-06 20:51:08", 
        "untranslated_entities": 0
    }, 
    "ru_RU": {
        "reviewed_percentage": "0%", 
        "completed": "17%", 
        "untranslated_words": 476, 
        "last_commiter": "", 
        "reviewed": 0, 
        "translated_entities": 23, 
        "translated_words": 51, 
        "last_update": "2016-03-06 20:52:39", 
        "untranslated_entities": 107
    }, 
    "is_IS": {
        "reviewed_percentage": "0%", 
        "completed": "17%", 
        "untranslated_words": 476, 
        "last_commiter": "", 
        "reviewed": 0, 
        "translated_entities": 23, 
        "translated_words": 51, 
        "last_update": "2016-03-06 20:52:39", 
        "untranslated_entities": 107
    }, 
    "km_KH": {
        "reviewed_percentage": "0%", 
        "completed": "0%", 
        "untranslated_words": 527, 
        "last_commiter": "", 
        "reviewed": 0, 
        "translated_entities": 0, 
        "translated_words": 0, 
        "last_update": "2016-03-06 20:51:08", 
        "untranslated_entities": 130
    }, 
    "zh_TW": {
        "reviewed_percentage": "0%", 
        "completed": "17%", 
        "untranslated_words": 476, 
        "last_commiter": "", 
        "reviewed": 0, 
        "translated_entities": 23, 
        "translated_words": 51, 
        "last_update": "2016-03-06 20:52:39", 
        "untranslated_entities": 107
    }, 
    "pt_BR": {
        "reviewed_percentage": "0%", 
        "completed": "100%", 
        "untranslated_words": 0, 
        "last_commiter": "waniltoncampos", 
        "reviewed": 0, 
        "translated_entities": 130, 
        "translated_words": 527, 
        "last_update": "2016-03-06 21:21:32", 
        "untranslated_entities": 0
    }, 
    "da_DK": {
        "reviewed_percentage": "0%", 
        "completed": "17%", 
        "untranslated_words": 476, 
        "last_commiter": "", 
        "reviewed": 0, 
        "translated_entities": 23, 
        "translated_words": 51, 
        "last_update": "2016-03-06 20:52:39", 
        "untranslated_entities": 107
    }, 
    "ko_KR": {
        "reviewed_percentage": "0%", 
        "completed": "17%", 
        "untranslated_words": 476, 
        "last_commiter": "", 
        "reviewed": 0, 
        "translated_entities": 23, 
        "translated_words": 51, 
        "last_update": "2016-03-06 20:52:39", 
        "untranslated_entities": 107
    }, 
    "mt_MT": {
        "reviewed_percentage": "0%", 
        "completed": "13%", 
        "untranslated_words": 493, 
        "last_commiter": "", 
        "reviewed": 0, 
        "translated_entities": 18, 
        "translated_words": 34, 
        "last_update": "2016-03-06 20:52:39", 
        "untranslated_entities": 112
    }, 
    "cs_CZ": {
        "reviewed_percentage": "0%", 
        "completed": "17%", 
        "untranslated_words": 476, 
        "last_commiter": "", 
        "reviewed": 0, 
        "translated_entities": 23, 
        "translated_words": 51, 
        "last_update": "2016-03-06 20:52:39", 
        "untranslated_entities": 107
    }, 
    "fo_FO": {
        "reviewed_percentage": "0%", 
        "completed": "6%", 
        "untranslated_words": 514, 
        "last_commiter": "", 
        "reviewed": 0, 
        "translated_entities": 8, 
        "translated_words": 13, 
        "last_update": "2016-03-06 20:52:39", 
        "untranslated_entities": 122
    }, 
    "tg_TJ": {
        "reviewed_percentage": "0%", 
        "completed": "7%", 
        "untranslated_words": 510, 
        "last_commiter": "", 
        "reviewed": 0, 
        "translated_entities": 10, 
        "translated_words": 17, 
        "last_update": "2016-03-06 20:52:39", 
        "untranslated_entities": 120
    }, 
    "tr_TR": {
        "reviewed_percentage": "0%", 
        "completed": "17%", 
        "untranslated_words": 476, 
        "last_commiter": "", 
        "reviewed": 0, 
        "translated_entities": 23, 
        "translated_words": 51, 
        "last_update": "2016-03-06 20:52:39", 
        "untranslated_entities": 107
    }, 
    "de_DE": {
        "reviewed_percentage": "0%", 
        "completed": "91%", 
        "untranslated_words": 113, 
        "last_commiter": "philipptemminghoff", 
        "reviewed": 0, 
        "translated_entities": 119, 
        "translated_words": 414, 
        "last_update": "2016-03-07 05:27:37", 
        "untranslated_entities": 11
    }, 
    "es_MX": {
        "reviewed_percentage": "0%", 
        "completed": "7%", 
        "untranslated_words": 510, 
        "last_commiter": "", 
        "reviewed": 0, 
        "translated_entities": 10, 
        "translated_words": 17, 
        "last_update": "2016-03-06 20:52:39", 
        "untranslated_entities": 120
    }, 
    "fa_AF": {
        "reviewed_percentage": "0%", 
        "completed": "0%", 
        "untranslated_words": 527, 
        "last_commiter": "", 
        "reviewed": 0, 
        "translated_entities": 0, 
        "translated_words": 0, 
        "last_update": "2016-03-06 20:51:08", 
        "untranslated_entities": 130
    }, 
    "he_IL": {
        "reviewed_percentage": "0%", 
        "completed": "17%", 
        "untranslated_words": 476, 
        "last_commiter": "", 
        "reviewed": 0, 
        "translated_entities": 23, 
        "translated_words": 51, 
        "last_update": "2016-03-06 20:52:39", 
        "untranslated_entities": 107
    }, 
    "fr_CA": {
        "reviewed_percentage": "0%", 
        "completed": "17%", 
        "untranslated_words": 476, 
        "last_commiter": "", 
        "reviewed": 0, 
        "translated_entities": 23, 
        "translated_words": 51, 
        "last_update": "2016-03-06 20:52:39", 
        "untranslated_entities": 107
    }, 
    "am_ET": {
        "reviewed_percentage": "0%", 
        "completed": "6%", 
        "untranslated_words": 511, 
        "last_commiter": "", 
        "reviewed": 0, 
        "translated_entities": 9, 
        "translated_words": 16, 
        "last_update": "2016-03-06 20:52:39", 
        "untranslated_entities": 121
    }, 
    "ms_MY": {
        "reviewed_percentage": "0%", 
        "completed": "17%", 
        "untranslated_words": 476, 
        "last_commiter": "", 
        "reviewed": 0, 
        "translated_entities": 23, 
        "translated_words": 51, 
        "last_update": "2016-03-06 20:52:39", 
        "untranslated_entities": 107
    }, 
    "bs_BA": {
        "reviewed_percentage": "0%", 
        "completed": "1%", 
        "untranslated_words": 524, 
        "last_commiter": "", 
        "reviewed": 0, 
        "translated_entities": 2, 
        "translated_words": 3, 
        "last_update": "2016-03-06 20:52:39", 
        "untranslated_entities": 128
    }, 
    "fa_IR": {
        "reviewed_percentage": "0%", 
        "completed": "13%", 
        "untranslated_words": 496, 
        "last_commiter": "", 
        "reviewed": 0, 
        "translated_entities": 17, 
        "translated_words": 31, 
        "last_update": "2016-03-06 20:52:39", 
        "untranslated_entities": 113
    }, 
    "zh_CN": {
        "reviewed_percentage": "0%", 
        "completed": "17%", 
        "untranslated_words": 476, 
        "last_commiter": "", 
        "reviewed": 0, 
        "translated_entities": 23, 
        "translated_words": 51, 
        "last_update": "2016-03-06 20:52:39", 
        "untranslated_entities": 107
    }, 
    "mn_MN": {
        "reviewed_percentage": "0%", 
        "completed": "1%", 
        "untranslated_words": 523, 
        "last_commiter": "", 
        "reviewed": 0, 
        "translated_entities": 2, 
        "translated_words": 4, 
        "last_update": "2016-03-06 20:52:39", 
        "untranslated_entities": 128
    }, 
    "mi": {
        "reviewed_percentage": "0%", 
        "completed": "1%", 
        "untranslated_words": 524, 
        "last_commiter": "", 
        "reviewed": 0, 
        "translated_entities": 2, 
        "translated_words": 3, 
        "last_update": "2016-03-06 20:52:39", 
        "untranslated_entities": 128
    }, 
    "si_LK": {
        "reviewed_percentage": "0%", 
        "completed": "0%", 
        "untranslated_words": 525, 
        "last_commiter": "", 
        "reviewed": 0, 
        "translated_entities": 1, 
        "translated_words": 2, 
        "last_update": "2016-03-06 20:52:39", 
        "untranslated_entities": 129
    }, 
    "my_MM": {
        "reviewed_percentage": "0%", 
        "completed": "3%", 
        "untranslated_words": 519, 
        "last_commiter": "", 
        "reviewed": 0, 
        "translated_entities": 5, 
        "translated_words": 8, 
        "last_update": "2016-03-06 20:52:39", 
        "untranslated_entities": 125
    }, 
    "sv_SE": {
        "reviewed_percentage": "0%", 
        "completed": "17%", 
        "untranslated_words": 476, 
        "last_commiter": "", 
        "reviewed": 0, 
        "translated_entities": 23, 
        "translated_words": 51, 
        "last_update": "2016-03-06 20:52:39", 
        "untranslated_entities": 107
    }, 
    "bg_BG": {
        "reviewed_percentage": "0%", 
        "completed": "17%", 
        "untranslated_words": 476, 
        "last_commiter": "", 
        "reviewed": 0, 
        "translated_entities": 23, 
        "translated_words": 51, 
        "last_update": "2016-03-06 20:52:39", 
        "untranslated_entities": 107
    }, 
    "ml_IN": {
        "reviewed_percentage": "0%", 
        "completed": "0%", 
        "untranslated_words": 527, 
        "last_commiter": "", 
        "reviewed": 0, 
        "translated_entities": 0, 
        "translated_words": 0, 
        "last_update": "2016-03-06 20:51:08", 
        "untranslated_entities": 130
    }, 
    "te_IN": {
        "reviewed_percentage": "0%", 
        "completed": "0%", 
        "untranslated_words": 527, 
        "last_commiter": "", 
        "reviewed": 0, 
        "translated_entities": 0, 
        "translated_words": 0, 
        "last_update": "2016-03-06 20:51:09", 
        "untranslated_entities": 130
    }, 
    "en_NZ": {
        "reviewed_percentage": "0%", 
        "completed": "17%", 
        "untranslated_words": 476, 
        "last_commiter": "", 
        "reviewed": 0, 
        "translated_entities": 23, 
        "translated_words": 51, 
        "last_update": "2016-03-06 20:52:39", 
        "untranslated_entities": 107
    }, 
    "hy_AM": {
        "reviewed_percentage": "0%", 
        "completed": "5%", 
        "untranslated_words": 516, 
        "last_commiter": "", 
        "reviewed": 0, 
        "translated_entities": 7, 
        "translated_words": 11, 
        "last_update": "2016-03-06 20:52:39", 
        "untranslated_entities": 123
    }, 
    "af_ZA": {
        "reviewed_percentage": "0%", 
        "completed": "17%", 
        "untranslated_words": 476, 
        "last_commiter": "", 
        "reviewed": 0, 
        "translated_entities": 23, 
        "translated_words": 51, 
        "last_update": "2016-03-06 20:52:39", 
        "untranslated_entities": 107
    }, 
    "nb_NO": {
        "reviewed_percentage": "0%", 
        "completed": "17%", 
        "untranslated_words": 476, 
        "last_commiter": "", 
        "reviewed": 0, 
        "translated_entities": 23, 
        "translated_words": 51, 
        "last_update": "2016-03-06 20:52:39", 
        "untranslated_entities": 107
    }, 
    "uz_UZ": {
        "reviewed_percentage": "0%", 
        "completed": "0%", 
        "untranslated_words": 525, 
        "last_commiter": "", 
        "reviewed": 0, 
        "translated_entities": 1, 
        "translated_words": 2, 
        "last_update": "2016-03-06 20:52:39", 
        "untranslated_entities": 129
    }, 
    "sq_AL": {
        "reviewed_percentage": "0%", 
        "completed": "6%", 
        "untranslated_words": 511, 
        "last_commiter": "", 
        "reviewed": 0, 
        "translated_entities": 9, 
        "translated_words": 16, 
        "last_update": "2016-03-06 20:52:39", 
        "untranslated_entities": 121
    }
}