{
    "ar_SA": {
        "reviewed_percentage": "0%", 
        "completed": "7%", 
        "untranslated_words": 553, 
        "last_commiter": "TeamKODI", 
        "reviewed": 0, 
        "translated_entities": 10, 
        "translated_words": 18, 
        "last_update": "2017-01-14 21:36:03", 
        "untranslated_entities": 125
    }, 
    "eo": {
        "reviewed_percentage": "0%", 
        "completed": "0%", 
        "untranslated_words": 571, 
        "last_commiter": "TeamKODI", 
        "reviewed": 0, 
        "translated_entities": 0, 
        "translated_words": 0, 
        "last_update": "2017-01-14 21:36:02", 
        "untranslated_entities": 135
    }, 
    "tr_TR": {
        "reviewed_percentage": "99%", 
        "completed": "100%", 
        "untranslated_words": 0, 
        "last_commiter": "TeamKODI", 
        "reviewed": 134, 
        "translated_entities": 135, 
        "translated_words": 571, 
        "last_update": "2017-01-14 21:36:05", 
        "untranslated_entities": 0
    }, 
    "fr_FR": {
        "reviewed_percentage": "0%", 
        "completed": "100%", 
        "untranslated_words": 0, 
        "last_commiter": "TeamKODI", 
        "reviewed": 0, 
        "translated_entities": 135, 
        "translated_words": 571, 
        "last_update": "2017-01-14 21:36:04", 
        "untranslated_entities": 0
    }, 
    "fi_FI": {
        "reviewed_percentage": "0%", 
        "completed": "100%", 
        "untranslated_words": 0, 
        "last_commiter": "TeamKODI", 
        "reviewed": 0, 
        "translated_entities": 135, 
        "translated_words": 571, 
        "last_update": "2017-01-14 21:36:04", 
        "untranslated_entities": 0
    }, 
    "id_ID": {
        "reviewed_percentage": "0%", 
        "completed": "17%", 
        "untranslated_words": 522, 
        "last_commiter": "TeamKODI", 
        "reviewed": 0, 
        "translated_entities": 23, 
        "translated_words": 49, 
        "last_update": "2017-01-14 21:36:04", 
        "untranslated_entities": 112
    }, 
    "pt_PT": {
        "reviewed_percentage": "0%", 
        "completed": "91%", 
        "untranslated_words": 75, 
        "last_commiter": "manuelarodsilva", 
        "reviewed": 0, 
        "translated_entities": 124, 
        "translated_words": 496, 
        "last_update": "2017-01-14 21:36:04", 
        "untranslated_entities": 11
    }, 
    "it_IT": {
        "reviewed_percentage": "0%", 
        "completed": "100%", 
        "untranslated_words": 0, 
        "last_commiter": "TeamKODI", 
        "reviewed": 0, 
        "translated_entities": 135, 
        "translated_words": 571, 
        "last_update": "2017-01-14 21:36:04", 
        "untranslated_entities": 0
    }, 
    "et_EE": {
        "reviewed_percentage": "0%", 
        "completed": "8%", 
        "untranslated_words": 552, 
        "last_commiter": "TeamKODI", 
        "reviewed": 0, 
        "translated_entities": 11, 
        "translated_words": 19, 
        "last_update": "2017-01-14 21:36:03", 
        "untranslated_entities": 124
    }, 
    "sr_RS": {
        "reviewed_percentage": "100%", 
        "completed": "100%", 
        "untranslated_words": 0, 
        "last_commiter": "vdb86", 
        "reviewed": 135, 
        "translated_entities": 135, 
        "translated_words": 571, 
        "last_update": "2017-01-22 16:40:02", 
        "untranslated_entities": 0
    }, 
    "vi_VN": {
        "reviewed_percentage": "0%", 
        "completed": "11%", 
        "untranslated_words": 543, 
        "last_commiter": "TeamKODI", 
        "reviewed": 0, 
        "translated_entities": 15, 
        "translated_words": 28, 
        "last_update": "2017-01-14 21:36:03", 
        "untranslated_entities": 120
    }, 
    "uk_UA": {
        "reviewed_percentage": "0%", 
        "completed": "99%", 
        "untranslated_words": 1, 
        "last_commiter": "TeamKODI", 
        "reviewed": 0, 
        "translated_entities": 134, 
        "translated_words": 570, 
        "last_update": "2017-01-14 21:36:04", 
        "untranslated_entities": 1
    }, 
    "en_NZ": {
        "reviewed_percentage": "0%", 
        "completed": "100%", 
        "untranslated_words": 0, 
        "last_commiter": "TeamKODI", 
        "reviewed": 0, 
        "translated_entities": 135, 
        "translated_words": 571, 
        "last_update": "2017-01-14 21:36:04", 
        "untranslated_entities": 0
    }, 
    "nl_NL": {
        "reviewed_percentage": "77%", 
        "completed": "100%", 
        "untranslated_words": 0, 
        "last_commiter": "TeamKODI", 
        "reviewed": 104, 
        "translated_entities": 135, 
        "translated_words": 571, 
        "last_update": "2017-01-14 21:36:04", 
        "untranslated_entities": 0
    }, 
    "en_US": {
        "reviewed_percentage": "0%", 
        "completed": "85%", 
        "untranslated_words": 96, 
        "last_commiter": "TeamKODI", 
        "reviewed": 0, 
        "translated_entities": 115, 
        "translated_words": 475, 
        "last_update": "2017-01-14 21:36:04", 
        "untranslated_entities": 20
    }, 
    "lv_LV": {
        "reviewed_percentage": "0%", 
        "completed": "46%", 
        "untranslated_words": 441, 
        "last_commiter": "TeamKODI", 
        "reviewed": 1, 
        "translated_entities": 63, 
        "translated_words": 130, 
        "last_update": "2017-01-14 21:36:03", 
        "untranslated_entities": 72
    }, 
    "el_GR": {
        "reviewed_percentage": "0%", 
        "completed": "94%", 
        "untranslated_words": 62, 
        "last_commiter": "TeamKODI", 
        "reviewed": 0, 
        "translated_entities": 128, 
        "translated_words": 509, 
        "last_update": "2017-01-14 21:36:04", 
        "untranslated_entities": 7
    }, 
    "cy_GB": {
        "reviewed_percentage": "0%", 
        "completed": "8%", 
        "untranslated_words": 552, 
        "last_commiter": "TeamKODI", 
        "reviewed": 0, 
        "translated_entities": 11, 
        "translated_words": 19, 
        "last_update": "2017-01-14 21:36:03", 
        "untranslated_entities": 124
    }, 
    "th_TH": {
        "reviewed_percentage": "0%", 
        "completed": "99%", 
        "untranslated_words": 1, 
        "last_commiter": "TeamKODI", 
        "reviewed": 0, 
        "translated_entities": 134, 
        "translated_words": 570, 
        "last_update": "2017-01-14 21:36:04", 
        "untranslated_entities": 1
    }, 
    "be_BY": {
        "reviewed_percentage": "0%", 
        "completed": "5%", 
        "untranslated_words": 558, 
        "last_commiter": "TeamKODI", 
        "reviewed": 0, 
        "translated_entities": 8, 
        "translated_words": 13, 
        "last_update": "2017-01-14 21:36:03", 
        "untranslated_entities": 127
    }, 
    "mk_MK": {
        "reviewed_percentage": "0%", 
        "completed": "9%", 
        "untranslated_words": 548, 
        "last_commiter": "TeamKODI", 
        "reviewed": 0, 
        "translated_entities": 13, 
        "translated_words": 23, 
        "last_update": "2017-01-14 21:36:03", 
        "untranslated_entities": 122
    }, 
    "ro_RO": {
        "reviewed_percentage": "0%", 
        "completed": "88%", 
        "untranslated_words": 60, 
        "last_commiter": "TeamKODI", 
        "reviewed": 0, 
        "translated_entities": 119, 
        "translated_words": 511, 
        "last_update": "2017-01-14 21:36:04", 
        "untranslated_entities": 16
    }, 
    "szl": {
        "reviewed_percentage": "0%", 
        "completed": "85%", 
        "untranslated_words": 96, 
        "last_commiter": "TeamKODI", 
        "reviewed": 0, 
        "translated_entities": 115, 
        "translated_words": 475, 
        "last_update": "2017-01-14 21:36:05", 
        "untranslated_entities": 20
    }, 
    "ca_ES": {
        "reviewed_percentage": "0%", 
        "completed": "99%", 
        "untranslated_words": 4, 
        "last_commiter": "rbuj", 
        "reviewed": 0, 
        "translated_entities": 134, 
        "translated_words": 567, 
        "last_update": "2017-01-14 21:36:04", 
        "untranslated_entities": 1
    }, 
    "az_AZ": {
        "reviewed_percentage": "0%", 
        "completed": "0%", 
        "untranslated_words": 570, 
        "last_commiter": "TeamKODI", 
        "reviewed": 0, 
        "translated_entities": 1, 
        "translated_words": 1, 
        "last_update": "2017-01-14 21:36:02", 
        "untranslated_entities": 134
    }, 
    "hi_IN": {
        "reviewed_percentage": "0%", 
        "completed": "0%", 
        "untranslated_words": 569, 
        "last_commiter": "TeamKODI", 
        "reviewed": 0, 
        "translated_entities": 1, 
        "translated_words": 2, 
        "last_update": "2017-01-14 21:36:02", 
        "untranslated_entities": 134
    }, 
    "sr_RS@latin": {
        "reviewed_percentage": "100%", 
        "completed": "100%", 
        "untranslated_words": 0, 
        "last_commiter": "vdb86", 
        "reviewed": 135, 
        "translated_entities": 135, 
        "translated_words": 571, 
        "last_update": "2017-01-22 17:40:19", 
        "untranslated_entities": 0
    }, 
    "en_AU": {
        "reviewed_percentage": "0%", 
        "completed": "8%", 
        "untranslated_words": 550, 
        "last_commiter": "TeamKODI", 
        "reviewed": 0, 
        "translated_entities": 12, 
        "translated_words": 21, 
        "last_update": "2017-01-14 21:36:03", 
        "untranslated_entities": 123
    }, 
    "hu_HU": {
        "reviewed_percentage": "0%", 
        "completed": "88%", 
        "untranslated_words": 60, 
        "last_commiter": "TeamKODI", 
        "reviewed": 0, 
        "translated_entities": 119, 
        "translated_words": 511, 
        "last_update": "2017-01-14 21:36:04", 
        "untranslated_entities": 16
    }, 
    "ja_JP": {
        "reviewed_percentage": "0%", 
        "completed": "79%", 
        "untranslated_words": 117, 
        "last_commiter": "TeamKODI", 
        "reviewed": 0, 
        "translated_entities": 107, 
        "translated_words": 454, 
        "last_update": "2017-01-14 21:36:03", 
        "untranslated_entities": 28
    }, 
    "lt_LT": {
        "reviewed_percentage": "0%", 
        "completed": "100%", 
        "untranslated_words": 0, 
        "last_commiter": "TeamKODI", 
        "reviewed": 0, 
        "translated_entities": 135, 
        "translated_words": 571, 
        "last_update": "2017-01-14 21:36:05", 
        "untranslated_entities": 0
    }, 
    "sl_SI": {
        "reviewed_percentage": "0%", 
        "completed": "18%", 
        "untranslated_words": 519, 
        "last_commiter": "TeamKODI", 
        "reviewed": 0, 
        "translated_entities": 25, 
        "translated_words": 52, 
        "last_update": "2017-01-28 15:09:18", 
        "untranslated_entities": 110
    }, 
    "hr_HR": {
        "reviewed_percentage": "97%", 
        "completed": "100%", 
        "untranslated_words": 0, 
        "last_commiter": "TeamKODI", 
        "reviewed": 131, 
        "translated_entities": 135, 
        "translated_words": 571, 
        "last_update": "2017-01-14 21:36:04", 
        "untranslated_entities": 0
    }, 
    "es_AR": {
        "reviewed_percentage": "98%", 
        "completed": "100%", 
        "untranslated_words": 0, 
        "last_commiter": "cramm", 
        "reviewed": 133, 
        "translated_entities": 135, 
        "translated_words": 571, 
        "last_update": "2017-01-21 17:11:23", 
        "untranslated_entities": 0
    }, 
    "eu_ES": {
        "reviewed_percentage": "0%", 
        "completed": "17%", 
        "untranslated_words": 522, 
        "last_commiter": "TeamKODI", 
        "reviewed": 0, 
        "translated_entities": 23, 
        "translated_words": 49, 
        "last_update": "2017-01-14 21:36:03", 
        "untranslated_entities": 112
    }, 
    "es_ES": {
        "reviewed_percentage": "0%", 
        "completed": "100%", 
        "untranslated_words": 0, 
        "last_commiter": "alfonskunk", 
        "reviewed": 0, 
        "translated_entities": 135, 
        "translated_words": 571, 
        "last_update": "2017-01-27 20:14:39", 
        "untranslated_entities": 0
    }, 
    "ru_RU": {
        "reviewed_percentage": "0%", 
        "completed": "100%", 
        "untranslated_words": 0, 
        "last_commiter": "TeamKODI", 
        "reviewed": 0, 
        "translated_entities": 135, 
        "translated_words": 571, 
        "last_update": "2017-01-14 21:36:05", 
        "untranslated_entities": 0
    }, 
    "gl_ES": {
        "reviewed_percentage": "0%", 
        "completed": "97%", 
        "untranslated_words": 9, 
        "last_commiter": "xurxo", 
        "reviewed": 0, 
        "translated_entities": 131, 
        "translated_words": 562, 
        "last_update": "2017-01-21 00:33:14", 
        "untranslated_entities": 4
    }, 
    "en_GB": {
        "reviewed_percentage": "0%", 
        "completed": "100%", 
        "untranslated_words": 0, 
        "last_commiter": "TeamKODI", 
        "reviewed": 0, 
        "translated_entities": 135, 
        "translated_words": 571, 
        "last_update": "2017-01-14 21:36:05", 
        "untranslated_entities": 0
    }, 
    "bg_BG": {
        "reviewed_percentage": "1%", 
        "completed": "73%", 
        "untranslated_words": 142, 
        "last_commiter": "TeamKODI", 
        "reviewed": 2, 
        "translated_entities": 99, 
        "translated_words": 429, 
        "last_update": "2017-01-14 21:36:03", 
        "untranslated_entities": 36
    }, 
    "is_IS": {
        "reviewed_percentage": "0%", 
        "completed": "17%", 
        "untranslated_words": 520, 
        "last_commiter": "TeamKODI", 
        "reviewed": 0, 
        "translated_entities": 24, 
        "translated_words": 51, 
        "last_update": "2017-01-14 21:36:04", 
        "untranslated_entities": 111
    }, 
    "zh_TW": {
        "reviewed_percentage": "0%", 
        "completed": "100%", 
        "untranslated_words": 0, 
        "last_commiter": "TeamKODI", 
        "reviewed": 0, 
        "translated_entities": 135, 
        "translated_words": 571, 
        "last_update": "2017-01-14 21:36:05", 
        "untranslated_entities": 0
    }, 
    "pt_BR": {
        "reviewed_percentage": "0%", 
        "completed": "100%", 
        "untranslated_words": 0, 
        "last_commiter": "TeamKODI", 
        "reviewed": 0, 
        "translated_entities": 135, 
        "translated_words": 571, 
        "last_update": "2017-01-14 21:36:04", 
        "untranslated_entities": 0
    }, 
    "ast_ES": {
        "reviewed_percentage": "0%", 
        "completed": "78%", 
        "untranslated_words": 96, 
        "last_commiter": "TeamKODI", 
        "reviewed": 0, 
        "translated_entities": 106, 
        "translated_words": 475, 
        "last_update": "2017-01-14 21:36:03", 
        "untranslated_entities": 29
    }, 
    "da_DK": {
        "reviewed_percentage": "0%", 
        "completed": "68%", 
        "untranslated_words": 320, 
        "last_commiter": "Meliox", 
        "reviewed": 0, 
        "translated_entities": 92, 
        "translated_words": 251, 
        "last_update": "2017-01-14 21:36:04", 
        "untranslated_entities": 43
    }, 
    "ko_KR": {
        "reviewed_percentage": "3%", 
        "completed": "88%", 
        "untranslated_words": 60, 
        "last_commiter": "TeamKODI", 
        "reviewed": 5, 
        "translated_entities": 119, 
        "translated_words": 511, 
        "last_update": "2017-01-14 21:36:04", 
        "untranslated_entities": 16
    }, 
    "mt_MT": {
        "reviewed_percentage": "0%", 
        "completed": "13%", 
        "untranslated_words": 538, 
        "last_commiter": "TeamKODI", 
        "reviewed": 0, 
        "translated_entities": 18, 
        "translated_words": 33, 
        "last_update": "2017-01-14 21:36:03", 
        "untranslated_entities": 117
    }, 
    "cs_CZ": {
        "reviewed_percentage": "0%", 
        "completed": "100%", 
        "untranslated_words": 0, 
        "last_commiter": "Trottel", 
        "reviewed": 0, 
        "translated_entities": 135, 
        "translated_words": 571, 
        "last_update": "2017-01-25 18:25:31", 
        "untranslated_entities": 0
    }, 
    "fo_FO": {
        "reviewed_percentage": "0%", 
        "completed": "4%", 
        "untranslated_words": 562, 
        "last_commiter": "TeamKODI", 
        "reviewed": 0, 
        "translated_entities": 6, 
        "translated_words": 9, 
        "last_update": "2017-01-14 21:36:02", 
        "untranslated_entities": 129
    }, 
    "sq_AL": {
        "reviewed_percentage": "0%", 
        "completed": "5%", 
        "untranslated_words": 559, 
        "last_commiter": "TeamKODI", 
        "reviewed": 0, 
        "translated_entities": 7, 
        "translated_words": 12, 
        "last_update": "2017-01-14 21:36:03", 
        "untranslated_entities": 128
    }, 
    "sk_SK": {
        "reviewed_percentage": "67%", 
        "completed": "100%", 
        "untranslated_words": 0, 
        "last_commiter": "euvlad93", 
        "reviewed": 91, 
        "translated_entities": 135, 
        "translated_words": 571, 
        "last_update": "2017-01-14 21:36:05", 
        "untranslated_entities": 0
    }, 
    "af_ZA": {
        "reviewed_percentage": "0%", 
        "completed": "100%", 
        "untranslated_words": 0, 
        "last_commiter": "TeamKODI", 
        "reviewed": 0, 
        "translated_entities": 135, 
        "translated_words": 571, 
        "last_update": "2017-01-14 21:36:04", 
        "untranslated_entities": 0
    }, 
    "de_DE": {
        "reviewed_percentage": "93%", 
        "completed": "100%", 
        "untranslated_words": 0, 
        "last_commiter": "TeamKODI", 
        "reviewed": 126, 
        "translated_entities": 135, 
        "translated_words": 571, 
        "last_update": "2017-01-14 21:36:04", 
        "untranslated_entities": 0
    }, 
    "es_MX": {
        "reviewed_percentage": "0%", 
        "completed": "100%", 
        "untranslated_words": 0, 
        "last_commiter": "TeamKODI", 
        "reviewed": 0, 
        "translated_entities": 135, 
        "translated_words": 571, 
        "last_update": "2017-01-14 21:36:04", 
        "untranslated_entities": 0
    }, 
    "fa_AF": {
        "reviewed_percentage": "0%", 
        "completed": "0%", 
        "untranslated_words": 570, 
        "last_commiter": "TeamKODI", 
        "reviewed": 0, 
        "translated_entities": 1, 
        "translated_words": 1, 
        "last_update": "2017-01-14 21:36:02", 
        "untranslated_entities": 134
    }, 
    "he_IL": {
        "reviewed_percentage": "0%", 
        "completed": "100%", 
        "untranslated_words": 0, 
        "last_commiter": "Shachar2like", 
        "reviewed": 0, 
        "translated_entities": 135, 
        "translated_words": 571, 
        "last_update": "2017-01-26 12:44:37", 
        "untranslated_entities": 0
    }, 
    "fr_CA": {
        "reviewed_percentage": "99%", 
        "completed": "100%", 
        "untranslated_words": 0, 
        "last_commiter": "TeamKODI", 
        "reviewed": 134, 
        "translated_entities": 135, 
        "translated_words": 571, 
        "last_update": "2017-01-14 21:36:04", 
        "untranslated_entities": 0
    }, 
    "am_ET": {
        "reviewed_percentage": "0%", 
        "completed": "9%", 
        "untranslated_words": 548, 
        "last_commiter": "TeamKODI", 
        "reviewed": 0, 
        "translated_entities": 13, 
        "translated_words": 23, 
        "last_update": "2017-01-14 21:36:03", 
        "untranslated_entities": 122
    }, 
    "ms_MY": {
        "reviewed_percentage": "0%", 
        "completed": "100%", 
        "untranslated_words": 0, 
        "last_commiter": "TeamKODI", 
        "reviewed": 0, 
        "translated_entities": 135, 
        "translated_words": 571, 
        "last_update": "2017-01-14 21:36:04", 
        "untranslated_entities": 0
    }, 
    "bs_BA": {
        "reviewed_percentage": "0%", 
        "completed": "0%", 
        "untranslated_words": 570, 
        "last_commiter": "TeamKODI", 
        "reviewed": 0, 
        "translated_entities": 1, 
        "translated_words": 1, 
        "last_update": "2017-01-14 21:36:02", 
        "untranslated_entities": 134
    }, 
    "fa_IR": {
        "reviewed_percentage": "0%", 
        "completed": "13%", 
        "untranslated_words": 539, 
        "last_commiter": "TeamKODI", 
        "reviewed": 0, 
        "translated_entities": 18, 
        "translated_words": 32, 
        "last_update": "2017-01-14 21:36:03", 
        "untranslated_entities": 117
    }, 
    "zh_CN": {
        "reviewed_percentage": "98%", 
        "completed": "100%", 
        "untranslated_words": 0, 
        "last_commiter": "TeamKODI", 
        "reviewed": 133, 
        "translated_entities": 135, 
        "translated_words": 571, 
        "last_update": "2017-01-14 21:36:05", 
        "untranslated_entities": 0
    }, 
    "mn_MN": {
        "reviewed_percentage": "0%", 
        "completed": "2%", 
        "untranslated_words": 566, 
        "last_commiter": "TeamKODI", 
        "reviewed": 0, 
        "translated_entities": 3, 
        "translated_words": 5, 
        "last_update": "2017-01-14 21:36:02", 
        "untranslated_entities": 132
    }, 
    "mi": {
        "reviewed_percentage": "0%", 
        "completed": "0%", 
        "untranslated_words": 570, 
        "last_commiter": "TeamKODI", 
        "reviewed": 0, 
        "translated_entities": 1, 
        "translated_words": 1, 
        "last_update": "2017-01-14 21:36:02", 
        "untranslated_entities": 134
    }, 
    "si_LK": {
        "reviewed_percentage": "0%", 
        "completed": "0%", 
        "untranslated_words": 571, 
        "last_commiter": "TeamKODI", 
        "reviewed": 0, 
        "translated_entities": 0, 
        "translated_words": 0, 
        "last_update": "2017-01-14 21:36:02", 
        "untranslated_entities": 135
    }, 
    "my_MM": {
        "reviewed_percentage": "0%", 
        "completed": "4%", 
        "untranslated_words": 562, 
        "last_commiter": "TeamKODI", 
        "reviewed": 0, 
        "translated_entities": 6, 
        "translated_words": 9, 
        "last_update": "2017-01-14 21:36:02", 
        "untranslated_entities": 129
    }, 
    "sv_SE": {
        "reviewed_percentage": "0%", 
        "completed": "100%", 
        "untranslated_words": 0, 
        "last_commiter": "andbo467", 
        "reviewed": 0, 
        "translated_entities": 135, 
        "translated_words": 571, 
        "last_update": "2017-01-27 19:45:04", 
        "untranslated_entities": 0
    }, 
    "ml_IN": {
        "reviewed_percentage": "0%", 
        "completed": "0%", 
        "untranslated_words": 571, 
        "last_commiter": "TeamKODI", 
        "reviewed": 0, 
        "translated_entities": 0, 
        "translated_words": 0, 
        "last_update": "2017-01-14 21:36:02", 
        "untranslated_entities": 135
    }, 
    "te_IN": {
        "reviewed_percentage": "0%", 
        "completed": "0%", 
        "untranslated_words": 571, 
        "last_commiter": "TeamKODI", 
        "reviewed": 0, 
        "translated_entities": 0, 
        "translated_words": 0, 
        "last_update": "2017-01-14 21:36:02", 
        "untranslated_entities": 135
    }, 
    "ta_IN": {
        "reviewed_percentage": "0%", 
        "completed": "5%", 
        "untranslated_words": 559, 
        "last_commiter": "TeamKODI", 
        "reviewed": 0, 
        "translated_entities": 7, 
        "translated_words": 12, 
        "last_update": "2017-01-14 21:36:03", 
        "untranslated_entities": 128
    }, 
    "hy_AM": {
        "reviewed_percentage": "0%", 
        "completed": "5%", 
        "untranslated_words": 557, 
        "last_commiter": "TeamKODI", 
        "reviewed": 0, 
        "translated_entities": 8, 
        "translated_words": 14, 
        "last_update": "2017-01-14 21:36:03", 
        "untranslated_entities": 127
    }, 
    "pl_PL": {
        "reviewed_percentage": "72%", 
        "completed": "100%", 
        "untranslated_words": 0, 
        "last_commiter": "TeamKODI", 
        "reviewed": 98, 
        "translated_entities": 135, 
        "translated_words": 571, 
        "last_update": "2017-01-14 21:36:04", 
        "untranslated_entities": 0
    }, 
    "nb_NO": {
        "reviewed_percentage": "0%", 
        "completed": "100%", 
        "untranslated_words": 0, 
        "last_commiter": "TeamKODI", 
        "reviewed": 0, 
        "translated_entities": 135, 
        "translated_words": 571, 
        "last_update": "2017-01-14 21:36:04", 
        "untranslated_entities": 0
    }, 
    "uz_UZ": {
        "reviewed_percentage": "0%", 
        "completed": "0%", 
        "untranslated_words": 570, 
        "last_commiter": "TeamKODI", 
        "reviewed": 0, 
        "translated_entities": 1, 
        "translated_words": 1, 
        "last_update": "2017-01-14 21:36:02", 
        "untranslated_entities": 134
    }, 
    "tg_TJ": {
        "reviewed_percentage": "0%", 
        "completed": "7%", 
        "untranslated_words": 553, 
        "last_commiter": "TeamKODI", 
        "reviewed": 0, 
        "translated_entities": 10, 
        "translated_words": 18, 
        "last_update": "2017-01-14 21:36:03", 
        "untranslated_entities": 125
    }
}