{
    "ar_SA": {
        "reviewed_percentage": "0%", 
        "completed": "56%", 
        "untranslated_words": 12425, 
        "last_commiter": "TeamKODI", 
        "reviewed": 0, 
        "translated_entities": 2233, 
        "translated_words": 5231, 
        "last_update": "2018-03-12 10:38:37", 
        "untranslated_entities": 1775
    }, 
    "eo": {
        "reviewed_percentage": "0%", 
        "completed": "25%", 
        "untranslated_words": 15446, 
        "last_commiter": "TeamKODI", 
        "reviewed": 0, 
        "translated_entities": 1011, 
        "translated_words": 2210, 
        "last_update": "2018-03-12 10:38:37", 
        "untranslated_entities": 2997
    }, 
    "sk_SK": {
        "reviewed_percentage": "26%", 
        "completed": "100%", 
        "untranslated_words": 0, 
        "last_commiter": "durovic.p", 
        "reviewed": 1038, 
        "translated_entities": 4008, 
        "translated_words": 17656, 
        "last_update": "2018-04-25 12:20:03", 
        "untranslated_entities": 0
    }, 
    "fr_FR": {
        "reviewed_percentage": "0%", 
        "completed": "100%", 
        "untranslated_words": 0, 
        "last_commiter": "Mati24", 
        "reviewed": 0, 
        "translated_entities": 4008, 
        "translated_words": 17656, 
        "last_update": "2018-04-21 06:29:58", 
        "untranslated_entities": 0
    }, 
    "fi_FI": {
        "reviewed_percentage": "0%", 
        "completed": "100%", 
        "untranslated_words": 0, 
        "last_commiter": "maxtherabbit", 
        "reviewed": 0, 
        "translated_entities": 4008, 
        "translated_words": 17656, 
        "last_update": "2018-03-12 12:58:45", 
        "untranslated_entities": 0
    }, 
    "hi_IN": {
        "reviewed_percentage": "0%", 
        "completed": "20%", 
        "untranslated_words": 16068, 
        "last_commiter": "TeamKODI", 
        "reviewed": 0, 
        "translated_entities": 793, 
        "translated_words": 1588, 
        "last_update": "2018-03-12 10:38:38", 
        "untranslated_entities": 3215
    }, 
    "pt_PT": {
        "reviewed_percentage": "0%", 
        "completed": "88%", 
        "untranslated_words": 2934, 
        "last_commiter": "TeamKODI", 
        "reviewed": 0, 
        "translated_entities": 3545, 
        "translated_words": 14722, 
        "last_update": "2018-03-12 10:38:39", 
        "untranslated_entities": 463
    }, 
    "it_IT": {
        "reviewed_percentage": "0%", 
        "completed": "100%", 
        "untranslated_words": 0, 
        "last_commiter": "Simograndi88", 
        "reviewed": 0, 
        "translated_entities": 4008, 
        "translated_words": 17656, 
        "last_update": "2018-04-02 13:48:01", 
        "untranslated_entities": 0
    }, 
    "et_EE": {
        "reviewed_percentage": "0%", 
        "completed": "78%", 
        "untranslated_words": 8484, 
        "last_commiter": "TeamKODI", 
        "reviewed": 0, 
        "translated_entities": 3126, 
        "translated_words": 9172, 
        "last_update": "2018-03-12 10:38:38", 
        "untranslated_entities": 882
    }, 
    "sr_RS": {
        "reviewed_percentage": "88%", 
        "completed": "91%", 
        "untranslated_words": 2139, 
        "last_commiter": "stalker", 
        "reviewed": 3546, 
        "translated_entities": 3629, 
        "translated_words": 15517, 
        "last_update": "2018-04-29 22:16:31", 
        "untranslated_entities": 379
    }, 
    "vi_VN": {
        "reviewed_percentage": "0%", 
        "completed": "44%", 
        "untranslated_words": 13789, 
        "last_commiter": "TeamKODI", 
        "reviewed": 0, 
        "translated_entities": 1783, 
        "translated_words": 3867, 
        "last_update": "2018-03-12 10:38:39", 
        "untranslated_entities": 2225
    }, 
    "uk_UA": {
        "reviewed_percentage": "0%", 
        "completed": "95%", 
        "untranslated_words": 3125, 
        "last_commiter": "romanvm", 
        "reviewed": 0, 
        "translated_entities": 3809, 
        "translated_words": 14531, 
        "last_update": "2018-04-19 17:10:23", 
        "untranslated_entities": 199
    }, 
    "en_NZ": {
        "reviewed_percentage": "0%", 
        "completed": "94%", 
        "untranslated_words": 1315, 
        "last_commiter": "TeamKODI", 
        "reviewed": 0, 
        "translated_entities": 3766, 
        "translated_words": 16341, 
        "last_update": "2018-03-12 10:38:39", 
        "untranslated_entities": 242
    }, 
    "nl_NL": {
        "reviewed_percentage": "100%", 
        "completed": "100%", 
        "untranslated_words": 0, 
        "last_commiter": "melledb", 
        "reviewed": 3997, 
        "translated_entities": 4008, 
        "translated_words": 17656, 
        "last_update": "2018-03-17 23:44:21", 
        "untranslated_entities": 0
    }, 
    "en_US": {
        "reviewed_percentage": "0%", 
        "completed": "100%", 
        "untranslated_words": 0, 
        "last_commiter": "forcedalias", 
        "reviewed": 0, 
        "translated_entities": 4008, 
        "translated_words": 17656, 
        "last_update": "2018-05-01 00:26:45", 
        "untranslated_entities": 0
    }, 
    "lv_LV": {
        "reviewed_percentage": "0%", 
        "completed": "66%", 
        "untranslated_words": 9809, 
        "last_commiter": "reptiilis", 
        "reviewed": 20, 
        "translated_entities": 2640, 
        "translated_words": 7847, 
        "last_update": "2018-04-09 10:08:18", 
        "untranslated_entities": 1368
    }, 
    "el_GR": {
        "reviewed_percentage": "0%", 
        "completed": "81%", 
        "untranslated_words": 7020, 
        "last_commiter": "spyrosag", 
        "reviewed": 0, 
        "translated_entities": 3242, 
        "translated_words": 10636, 
        "last_update": "2018-04-01 18:45:39", 
        "untranslated_entities": 766
    }, 
    "cy_GB": {
        "reviewed_percentage": "0%", 
        "completed": "68%", 
        "untranslated_words": 10075, 
        "last_commiter": "TeamKODI", 
        "reviewed": 0, 
        "translated_entities": 2739, 
        "translated_words": 7581, 
        "last_update": "2018-03-12 10:38:39", 
        "untranslated_entities": 1269
    }, 
    "th_TH": {
        "reviewed_percentage": "0%", 
        "completed": "89%", 
        "untranslated_words": 2367, 
        "last_commiter": "TeamKODI", 
        "reviewed": 0, 
        "translated_entities": 3561, 
        "translated_words": 15289, 
        "last_update": "2018-03-12 10:38:39", 
        "untranslated_entities": 447
    }, 
    "be_BY": {
        "reviewed_percentage": "0%", 
        "completed": "59%", 
        "untranslated_words": 11808, 
        "last_commiter": "victorenator", 
        "reviewed": 0, 
        "translated_entities": 2380, 
        "translated_words": 5848, 
        "last_update": "2018-05-03 20:56:32", 
        "untranslated_entities": 1628
    }, 
    "mk_MK": {
        "reviewed_percentage": "0%", 
        "completed": "65%", 
        "untranslated_words": 11557, 
        "last_commiter": "TeamKODI", 
        "reviewed": 0, 
        "translated_entities": 2624, 
        "translated_words": 6099, 
        "last_update": "2018-03-12 10:38:38", 
        "untranslated_entities": 1384
    }, 
    "ro_RO": {
        "reviewed_percentage": "0%", 
        "completed": "94%", 
        "untranslated_words": 1634, 
        "last_commiter": "TeamKODI", 
        "reviewed": 0, 
        "translated_entities": 3777, 
        "translated_words": 16022, 
        "last_update": "2018-03-12 10:38:39", 
        "untranslated_entities": 231
    }, 
    "szl": {
        "reviewed_percentage": "2%", 
        "completed": "88%", 
        "untranslated_words": 3003, 
        "last_commiter": "TeamKODI", 
        "reviewed": 71, 
        "translated_entities": 3516, 
        "translated_words": 14653, 
        "last_update": "2018-03-12 10:38:39", 
        "untranslated_entities": 492
    }, 
    "ca_ES": {
        "reviewed_percentage": "3%", 
        "completed": "89%", 
        "untranslated_words": 5156, 
        "last_commiter": "TeamKODI", 
        "reviewed": 110, 
        "translated_entities": 3551, 
        "translated_words": 12500, 
        "last_update": "2018-03-12 10:38:37", 
        "untranslated_entities": 457
    }, 
    "az_AZ": {
        "reviewed_percentage": "0%", 
        "completed": "12%", 
        "untranslated_words": 16936, 
        "last_commiter": "TeamKODI", 
        "reviewed": 0, 
        "translated_entities": 475, 
        "translated_words": 720, 
        "last_update": "2018-03-12 10:38:37", 
        "untranslated_entities": 3533
    }, 
    "id_ID": {
        "reviewed_percentage": "0%", 
        "completed": "75%", 
        "untranslated_words": 7892, 
        "last_commiter": "TeamKODI", 
        "reviewed": 0, 
        "translated_entities": 3017, 
        "translated_words": 9764, 
        "last_update": "2018-03-12 10:38:38", 
        "untranslated_entities": 991
    }, 
    "sr_RS@latin": {
        "reviewed_percentage": "88%", 
        "completed": "89%", 
        "untranslated_words": 2305, 
        "last_commiter": "TeamKODI", 
        "reviewed": 3546, 
        "translated_entities": 3569, 
        "translated_words": 15351, 
        "last_update": "2018-03-12 10:38:39", 
        "untranslated_entities": 439
    }, 
    "en_AU": {
        "reviewed_percentage": "0%", 
        "completed": "60%", 
        "untranslated_words": 10850, 
        "last_commiter": "TeamKODI", 
        "reviewed": 0, 
        "translated_entities": 2407, 
        "translated_words": 6806, 
        "last_update": "2018-03-12 10:38:37", 
        "untranslated_entities": 1601
    }, 
    "hu_HU": {
        "reviewed_percentage": "87%", 
        "completed": "100%", 
        "untranslated_words": 0, 
        "last_commiter": "meskobalazs", 
        "reviewed": 3489, 
        "translated_entities": 4008, 
        "translated_words": 17656, 
        "last_update": "2018-04-30 11:00:07", 
        "untranslated_entities": 0
    }, 
    "ja_JP": {
        "reviewed_percentage": "7%", 
        "completed": "79%", 
        "untranslated_words": 8107, 
        "last_commiter": "TeamKODI", 
        "reviewed": 284, 
        "translated_entities": 3158, 
        "translated_words": 9549, 
        "last_update": "2018-03-12 10:38:38", 
        "untranslated_entities": 850
    }, 
    "lt_LT": {
        "reviewed_percentage": "0%", 
        "completed": "100%", 
        "untranslated_words": 0, 
        "last_commiter": "ArtX38", 
        "reviewed": 0, 
        "translated_entities": 4008, 
        "translated_words": 17656, 
        "last_update": "2018-04-23 06:25:53", 
        "untranslated_entities": 0
    }, 
    "sl_SI": {
        "reviewed_percentage": "0%", 
        "completed": "75%", 
        "untranslated_words": 8808, 
        "last_commiter": "stefan.b", 
        "reviewed": 0, 
        "translated_entities": 3010, 
        "translated_words": 8848, 
        "last_update": "2018-05-04 07:01:20", 
        "untranslated_entities": 998
    }, 
    "hr_HR": {
        "reviewed_percentage": "99%", 
        "completed": "100%", 
        "untranslated_words": 41, 
        "last_commiter": "Doktor_X", 
        "reviewed": 3954, 
        "translated_entities": 4001, 
        "translated_words": 17615, 
        "last_update": "2018-03-21 11:43:14", 
        "untranslated_entities": 7
    }, 
    "es_AR": {
        "reviewed_percentage": "22%", 
        "completed": "88%", 
        "untranslated_words": 4001, 
        "last_commiter": "TeamKODI", 
        "reviewed": 898, 
        "translated_entities": 3519, 
        "translated_words": 13655, 
        "last_update": "2018-03-12 10:38:36", 
        "untranslated_entities": 489
    }, 
    "eu_ES": {
        "reviewed_percentage": "0%", 
        "completed": "88%", 
        "untranslated_words": 6119, 
        "last_commiter": "TeamKODI", 
        "reviewed": 0, 
        "translated_entities": 3536, 
        "translated_words": 11537, 
        "last_update": "2018-03-12 10:38:37", 
        "untranslated_entities": 472
    }, 
    "es_ES": {
        "reviewed_percentage": "0%", 
        "completed": "100%", 
        "untranslated_words": 0, 
        "last_commiter": "alfonskunk", 
        "reviewed": 18, 
        "translated_entities": 4008, 
        "translated_words": 17656, 
        "last_update": "2018-03-12 16:44:42", 
        "untranslated_entities": 0
    }, 
    "gl_ES": {
        "reviewed_percentage": "0%", 
        "completed": "97%", 
        "untranslated_words": 863, 
        "last_commiter": "TeamKODI", 
        "reviewed": 0, 
        "translated_entities": 3876, 
        "translated_words": 16793, 
        "last_update": "2018-03-12 10:38:38", 
        "untranslated_entities": 132
    }, 
    "en_GB": {
        "reviewed_percentage": "0%", 
        "completed": "100%", 
        "untranslated_words": 0, 
        "last_commiter": "TeamKODI", 
        "reviewed": 0, 
        "translated_entities": 4008, 
        "translated_words": 17656, 
        "last_update": "2018-03-12 10:38:36", 
        "untranslated_entities": 0
    }, 
    "ru_RU": {
        "reviewed_percentage": "0%", 
        "completed": "97%", 
        "untranslated_words": 1211, 
        "last_commiter": "romanvm", 
        "reviewed": 0, 
        "translated_entities": 3891, 
        "translated_words": 16445, 
        "last_update": "2018-05-06 18:15:08", 
        "untranslated_entities": 117
    }, 
    "is_IS": {
        "reviewed_percentage": "0%", 
        "completed": "99%", 
        "untranslated_words": 1050, 
        "last_commiter": "sveinki", 
        "reviewed": 0, 
        "translated_entities": 3982, 
        "translated_words": 16606, 
        "last_update": "2018-04-23 13:39:03", 
        "untranslated_entities": 26
    }, 
    "zh_TW": {
        "reviewed_percentage": "0%", 
        "completed": "100%", 
        "untranslated_words": 0, 
        "last_commiter": "chao_tw", 
        "reviewed": 0, 
        "translated_entities": 4008, 
        "translated_words": 17656, 
        "last_update": "2018-04-17 10:25:05", 
        "untranslated_entities": 0
    }, 
    "pt_BR": {
        "reviewed_percentage": "0%", 
        "completed": "100%", 
        "untranslated_words": 0, 
        "last_commiter": "waniltoncampos", 
        "reviewed": 1, 
        "translated_entities": 4008, 
        "translated_words": 17656, 
        "last_update": "2018-04-21 19:40:01", 
        "untranslated_entities": 0
    }, 
    "da_DK": {
        "reviewed_percentage": "0%", 
        "completed": "98%", 
        "untranslated_words": 1997, 
        "last_commiter": "Gade", 
        "reviewed": 0, 
        "translated_entities": 3914, 
        "translated_words": 15659, 
        "last_update": "2018-04-10 16:09:30", 
        "untranslated_entities": 94
    }, 
    "ko_KR": {
        "reviewed_percentage": "18%", 
        "completed": "89%", 
        "untranslated_words": 2723, 
        "last_commiter": "TeamKODI", 
        "reviewed": 731, 
        "translated_entities": 3557, 
        "translated_words": 14933, 
        "last_update": "2018-03-12 10:38:38", 
        "untranslated_entities": 451
    }, 
    "mt_MT": {
        "reviewed_percentage": "0%", 
        "completed": "74%", 
        "untranslated_words": 6338, 
        "last_commiter": "TeamKODI", 
        "reviewed": 0, 
        "translated_entities": 2981, 
        "translated_words": 11318, 
        "last_update": "2018-03-12 10:38:38", 
        "untranslated_entities": 1027
    }, 
    "cs_CZ": {
        "reviewed_percentage": "0%", 
        "completed": "100%", 
        "untranslated_words": 0, 
        "last_commiter": "Trottel", 
        "reviewed": 0, 
        "translated_entities": 4008, 
        "translated_words": 17656, 
        "last_update": "2018-04-28 14:22:20", 
        "untranslated_entities": 0
    }, 
    "fo_FO": {
        "reviewed_percentage": "0%", 
        "completed": "43%", 
        "untranslated_words": 13834, 
        "last_commiter": "TeamKODI", 
        "reviewed": 0, 
        "translated_entities": 1715, 
        "translated_words": 3822, 
        "last_update": "2018-03-12 10:38:38", 
        "untranslated_entities": 2293
    }, 
    "ms_MY": {
        "reviewed_percentage": "0%", 
        "completed": "100%", 
        "untranslated_words": 0, 
        "last_commiter": "abuyop", 
        "reviewed": 0, 
        "translated_entities": 4008, 
        "translated_words": 17656, 
        "last_update": "2018-03-17 16:10:10", 
        "untranslated_entities": 0
    }, 
    "sq_AL": {
        "reviewed_percentage": "0%", 
        "completed": "51%", 
        "untranslated_words": 13080, 
        "last_commiter": "TeamKODI", 
        "reviewed": 0, 
        "translated_entities": 2060, 
        "translated_words": 4576, 
        "last_update": "2018-03-12 10:38:37", 
        "untranslated_entities": 1948
    }, 
    "tr_TR": {
        "reviewed_percentage": "94%", 
        "completed": "97%", 
        "untranslated_words": 885, 
        "last_commiter": "TeamKODI", 
        "reviewed": 3764, 
        "translated_entities": 3875, 
        "translated_words": 16771, 
        "last_update": "2018-03-12 10:38:39", 
        "untranslated_entities": 133
    }, 
    "af_ZA": {
        "reviewed_percentage": "0%", 
        "completed": "89%", 
        "untranslated_words": 2945, 
        "last_commiter": "TeamKODI", 
        "reviewed": 0, 
        "translated_entities": 3556, 
        "translated_words": 14711, 
        "last_update": "2018-03-12 10:38:37", 
        "untranslated_entities": 452
    }, 
    "de_DE": {
        "reviewed_percentage": "93%", 
        "completed": "100%", 
        "untranslated_words": 155, 
        "last_commiter": "ksooo", 
        "reviewed": 3747, 
        "translated_entities": 4004, 
        "translated_words": 17501, 
        "last_update": "2018-04-17 21:36:54", 
        "untranslated_entities": 4
    }, 
    "es_MX": {
        "reviewed_percentage": "0%", 
        "completed": "88%", 
        "untranslated_words": 2594, 
        "last_commiter": "TeamKODI", 
        "reviewed": 0, 
        "translated_entities": 3538, 
        "translated_words": 15062, 
        "last_update": "2018-03-12 10:38:37", 
        "untranslated_entities": 470
    }, 
    "fa_AF": {
        "reviewed_percentage": "0%", 
        "completed": "7%", 
        "untranslated_words": 17327, 
        "last_commiter": "TeamKODI", 
        "reviewed": 0, 
        "translated_entities": 275, 
        "translated_words": 329, 
        "last_update": "2018-03-12 10:38:39", 
        "untranslated_entities": 3733
    }, 
    "he_IL": {
        "reviewed_percentage": "79%", 
        "completed": "96%", 
        "untranslated_words": 822, 
        "last_commiter": "TeamKODI", 
        "reviewed": 3149, 
        "translated_entities": 3836, 
        "translated_words": 16834, 
        "last_update": "2018-03-12 10:38:38", 
        "untranslated_entities": 172
    }, 
    "fr_CA": {
        "reviewed_percentage": "100%", 
        "completed": "100%", 
        "untranslated_words": 0, 
        "last_commiter": "yahoe.001", 
        "reviewed": 4008, 
        "translated_entities": 4008, 
        "translated_words": 17656, 
        "last_update": "2018-04-02 01:13:41", 
        "untranslated_entities": 0
    }, 
    "am_ET": {
        "reviewed_percentage": "0%", 
        "completed": "50%", 
        "untranslated_words": 13660, 
        "last_commiter": "samson", 
        "reviewed": 2, 
        "translated_entities": 2005, 
        "translated_words": 3996, 
        "last_update": "2018-05-02 18:58:02", 
        "untranslated_entities": 2003
    }, 
    "ast_ES": {
        "reviewed_percentage": "0%", 
        "completed": "43%", 
        "untranslated_words": 12412, 
        "last_commiter": "enolp", 
        "reviewed": 0, 
        "translated_entities": 1739, 
        "translated_words": 5244, 
        "last_update": "2018-05-02 19:06:49", 
        "untranslated_entities": 2269
    }, 
    "bs_BA": {
        "reviewed_percentage": "0%", 
        "completed": "47%", 
        "untranslated_words": 13517, 
        "last_commiter": "TeamKODI", 
        "reviewed": 0, 
        "translated_entities": 1887, 
        "translated_words": 4139, 
        "last_update": "2018-03-12 10:38:37", 
        "untranslated_entities": 2121
    }, 
    "fa_IR": {
        "reviewed_percentage": "0%", 
        "completed": "53%", 
        "untranslated_words": 12503, 
        "last_commiter": "TeamKODI", 
        "reviewed": 0, 
        "translated_entities": 2114, 
        "translated_words": 5153, 
        "last_update": "2018-03-12 10:38:38", 
        "untranslated_entities": 1894
    }, 
    "zh_CN": {
        "reviewed_percentage": "99%", 
        "completed": "100%", 
        "untranslated_words": 0, 
        "last_commiter": "wwj402", 
        "reviewed": 3966, 
        "translated_entities": 4008, 
        "translated_words": 17656, 
        "last_update": "2018-04-17 08:30:42", 
        "untranslated_entities": 0
    }, 
    "mn_MN": {
        "reviewed_percentage": "0%", 
        "completed": "20%", 
        "untranslated_words": 16288, 
        "last_commiter": "TeamKODI", 
        "reviewed": 16, 
        "translated_entities": 799, 
        "translated_words": 1368, 
        "last_update": "2018-03-12 10:38:38", 
        "untranslated_entities": 3209
    }, 
    "mi": {
        "reviewed_percentage": "0%", 
        "completed": "56%", 
        "untranslated_words": 12060, 
        "last_commiter": "TeamKODI", 
        "reviewed": 0, 
        "translated_entities": 2233, 
        "translated_words": 5596, 
        "last_update": "2018-03-12 10:38:37", 
        "untranslated_entities": 1775
    }, 
    "si_LK": {
        "reviewed_percentage": "0%", 
        "completed": "32%", 
        "untranslated_words": 15042, 
        "last_commiter": "TeamKODI", 
        "reviewed": 0, 
        "translated_entities": 1263, 
        "translated_words": 2614, 
        "last_update": "2018-03-12 10:38:39", 
        "untranslated_entities": 2745
    }, 
    "my_MM": {
        "reviewed_percentage": "0%", 
        "completed": "32%", 
        "untranslated_words": 15211, 
        "last_commiter": "TeamKODI", 
        "reviewed": 0, 
        "translated_entities": 1275, 
        "translated_words": 2445, 
        "last_update": "2018-03-12 10:38:37", 
        "untranslated_entities": 2733
    }, 
    "sv_SE": {
        "reviewed_percentage": "96%", 
        "completed": "100%", 
        "untranslated_words": 0, 
        "last_commiter": "andbo467", 
        "reviewed": 3859, 
        "translated_entities": 4008, 
        "translated_words": 17656, 
        "last_update": "2018-04-15 11:47:33", 
        "untranslated_entities": 0
    }, 
    "bg_BG": {
        "reviewed_percentage": "27%", 
        "completed": "100%", 
        "untranslated_words": 0, 
        "last_commiter": "NEOhidra", 
        "reviewed": 1065, 
        "translated_entities": 4008, 
        "translated_words": 17656, 
        "last_update": "2018-04-18 20:39:33", 
        "untranslated_entities": 0
    }, 
    "ml_IN": {
        "reviewed_percentage": "0%", 
        "completed": "5%", 
        "untranslated_words": 17382, 
        "last_commiter": "TeamKODI", 
        "reviewed": 0, 
        "translated_entities": 218, 
        "translated_words": 274, 
        "last_update": "2018-03-12 10:38:38", 
        "untranslated_entities": 3790
    }, 
    "te_IN": {
        "reviewed_percentage": "0%", 
        "completed": "10%", 
        "untranslated_words": 17023, 
        "last_commiter": "TeamKODI", 
        "reviewed": 0, 
        "translated_entities": 398, 
        "translated_words": 633, 
        "last_update": "2018-03-12 10:38:39", 
        "untranslated_entities": 3610
    }, 
    "ta_IN": {
        "reviewed_percentage": "0%", 
        "completed": "57%", 
        "untranslated_words": 12332, 
        "last_commiter": "TeamKODI", 
        "reviewed": 0, 
        "translated_entities": 2293, 
        "translated_words": 5324, 
        "last_update": "2018-03-12 10:38:39", 
        "untranslated_entities": 1715
    }, 
    "hy_AM": {
        "reviewed_percentage": "0%", 
        "completed": "15%", 
        "untranslated_words": 16635, 
        "last_commiter": "TeamKODI", 
        "reviewed": 0, 
        "translated_entities": 611, 
        "translated_words": 1021, 
        "last_update": "2018-03-12 10:38:37", 
        "untranslated_entities": 3397
    }, 
    "pl_PL": {
        "reviewed_percentage": "61%", 
        "completed": "99%", 
        "untranslated_words": 337, 
        "last_commiter": "TeamKODI", 
        "reviewed": 2438, 
        "translated_entities": 3964, 
        "translated_words": 17319, 
        "last_update": "2018-03-12 10:38:39", 
        "untranslated_entities": 44
    }, 
    "nb_NO": {
        "reviewed_percentage": "4%", 
        "completed": "98%", 
        "untranslated_words": 447, 
        "last_commiter": "TeamKODI", 
        "reviewed": 177, 
        "translated_entities": 3944, 
        "translated_words": 17209, 
        "last_update": "2018-03-12 10:38:38", 
        "untranslated_entities": 64
    }, 
    "uz_UZ": {
        "reviewed_percentage": "0%", 
        "completed": "24%", 
        "untranslated_words": 15788, 
        "last_commiter": "TeamKODI", 
        "reviewed": 6, 
        "translated_entities": 981, 
        "translated_words": 1868, 
        "last_update": "2018-03-12 10:38:39", 
        "untranslated_entities": 3027
    }, 
    "tg_TJ": {
        "reviewed_percentage": "0%", 
        "completed": "57%", 
        "untranslated_words": 11850, 
        "last_commiter": "TeamKODI", 
        "reviewed": 0, 
        "translated_entities": 2292, 
        "translated_words": 5806, 
        "last_update": "2018-03-12 10:38:39", 
        "untranslated_entities": 1716
    }
}